matrixdriver/__init__.py
matrixdriver/matrixdriver.py
matrixdriver-0.9.0.dist-info/DESCRIPTION.rst
matrixdriver-0.9.0.dist-info/METADATA
matrixdriver-0.9.0.dist-info/RECORD
matrixdriver-0.9.0.dist-info/WHEEL
matrixdriver-0.9.0.dist-info/entry_points.txt
matrixdriver-0.9.0.dist-info/metadata.json
matrixdriver-0.9.0.dist-info/top_level.txt
matrixdriver-0.9.0.dist-info/zip-safe
